CHANGES.txt
README.txt
bootstrap.py
buildout.cfg
setup.py
wildcard/__init__.py
wildcard.recipe.insertinto.egg-info/PKG-INFO
wildcard.recipe.insertinto.egg-info/SOURCES.txt
wildcard.recipe.insertinto.egg-info/dependency_links.txt
wildcard.recipe.insertinto.egg-info/entry_points.txt
wildcard.recipe.insertinto.egg-info/namespace_packages.txt
wildcard.recipe.insertinto.egg-info/not-zip-safe
wildcard.recipe.insertinto.egg-info/requires.txt
wildcard.recipe.insertinto.egg-info/top_level.txt
wildcard/recipe/__init__.py
wildcard/recipe/insertinto/__init__.py
wildcard/recipe/insertinto/tests/__init__.py
wildcard/recipe/insertinto/tests/test_docs.py