Metadata-Version: 1.0
Name: wildcard.recipe.insertinto
Version: 1.0a1
Summary: allow you to insert text into files
Home-page: UNKNOWN
Author: Nathan Van Gheem
Author-email: nathan.vangheem@wildcardcorp.com
License: ZPL
Keywords: buildout insert file
Platform: UNKNOWN
Classifier: Framework :: Buildout
Classifier: Intended Audience :: Developers
Classifier: Topic :: Software Development :: Build Tools
Classifier: Topic :: Software Development :: Libraries :: Python Modules
Classifier: License :: OSI Approved :: Zope Public License
